Total_Game/Total_Game.py
Total_Game/__init__.py
Total_Game-0.1.4.dist-info/LICENSE
Total_Game-0.1.4.dist-info/METADATA
Total_Game-0.1.4.dist-info/WHEEL
Total_Game-0.1.4.dist-info/top_level.txt
Total_Game-0.1.4.dist-info/RECORD
